LICENSE
README.md
setup.cfg
setup.py
llpdf/EncodeDecode.py
llpdf/Exceptions.py
llpdf/FileRepr.py
llpdf/Logging.py
llpdf/Measurements.py
llpdf/PDFDocument.py
llpdf/PDFReader.py
llpdf/PDFTemplate.py
llpdf/PDFWriter.py
llpdf/__init__.py
llpdf/filters/AddCropBoxFilter.py
llpdf/filters/AnalyzeFilter.py
llpdf/filters/DecompressFilter.py
llpdf/filters/DeleteOrphanedObjectsFilter.py
llpdf/filters/DownscaleImageOptimization.py
llpdf/filters/EmbedPayloadFilter.py
llpdf/filters/ExplicitLengthFilter.py
llpdf/filters/FlattenImageOptimization.py
llpdf/filters/PDFAFilter.py
llpdf/filters/PDFFilter.py
llpdf/filters/Relinker.py
llpdf/filters/RemoveDuplicateImageOptimization.py
llpdf/filters/RemoveMetadataFilter.py
llpdf/filters/SignFilter.py
llpdf/filters/TagFilter.py
llpdf/filters/__init__.py
llpdf/font/PostScriptEnums.py
llpdf/font/T1Canvas.py
llpdf/font/T1Command.py
llpdf/font/T1Font.py
llpdf/font/T1Glyph.py
llpdf/font/T1Interpreter.py
llpdf/font/T1PRNG.py
llpdf/font/TextWrapper.py
llpdf/font/__init__.py
llpdf/highlvl/PDFFunctions.py
llpdf/highlvl/PDFImageFunctions.py
llpdf/highlvl/__init__.py
llpdf/img/ImageReformatter.py
llpdf/img/NamedVector.py
llpdf/img/PDFExtImage.py
llpdf/img/PDFImage.py
llpdf/img/PnmPicture.py
llpdf/img/__init__.py
llpdf/interpreter/GraphicsInterpreter.py
llpdf/interpreter/__init__.py
llpdf/repr/GraphicsParser.py
llpdf/repr/PDFParser.py
llpdf/repr/PDFSerializer.py
llpdf/repr/ParseTools.py
llpdf/repr/__init__.py
llpdf/repr/tpg.py
llpdf/resources/__init__.py
llpdf/tests/EncodeDecodeTest.py
llpdf/tests/GraphicsParserTest.py
llpdf/tests/OpenSSLVersionTests.py
llpdf/tests/PDFParserTest.py
llpdf/tests/__init__.py
llpdf/tests/__main__.py
llpdf/tools/OpenSSLVersion.py
llpdf/tools/X509Certificate.py
llpdf/tools/__init__.py
llpdf/types/Comparable.py
llpdf/types/CompressedObjectContainer.py
llpdf/types/Flags.py
llpdf/types/MarkerObject.py
llpdf/types/PDFName.py
llpdf/types/PDFObject.py
llpdf/types/PDFStream.py
llpdf/types/PDFString.py
llpdf/types/PDFXRef.py
pdfminify.egg-info/PKG-INFO
pdfminify.egg-info/SOURCES.txt
pdfminify.egg-info/dependency_links.txt
pdfminify.egg-info/entry_points.txt
pdfminify.egg-info/requires.txt
pdfminify.egg-info/top_level.txt